Metadata-Version: 1.1
Name: save-and-learn-cli
Version: 1.0.0
Summary: The save-and-learn CLI.
Home-page: https://github.com/damienld22/save-and-learn
Author: Damien Le Dantec
Author-email: damien-le-dantec@hotmail.fr
License: UNLICENSE
Keywords: cli
Platform: UNKNOWN
Classifier: Intended Audience :: Developers
Classifier: Topic :: Utilities
Classifier: License :: Public Domain
Classifier: Natural Language :: English
Classifier: Operating System :: OS Independent
Classifier: Programming Language :: Python :: 3
Classifier: Programming Language :: Python :: 3.2
Classifier: Programming Language :: Python :: 3.3
Classifier: Programming Language :: Python :: 3.5
Classifier: Programming Language :: Python :: 3.6
Classifier: Programming Language :: Python :: 3.7
